README.md
setup.cfg
setup.py
AdvPyProject_1.egg-info/PKG-INFO
AdvPyProject_1.egg-info/SOURCES.txt
AdvPyProject_1.egg-info/dependency_links.txt
AdvPyProject_1.egg-info/requires.txt
AdvPyProject_1.egg-info/top_level.txt
mypackage/__init__.py
mypackage/mymodule.py
mypackage/template.txt