Metadata-Version: 1.1
Name: AdvPyProject-1
Version: 0.5.3
Summary: This should be a short description of our project
Home-page: https://github.com/mniswonger
Author: Some Person
Author-email: somebody@example.com
License: UNKNOWN
Keywords: test,class
Platform: UNKNOWN
Classifier: Programming Language :: Python :: 3
Classifier: Programming Language :: Python :: 3.7
